triton/FileCheck
triton/__init__.py
triton/_filecheck.py
triton/_internal_testing.py
triton/_utils.py
triton/errors.py
triton/knobs.py
triton/testing.py
triton/_C/libSanitizerAttributes.so
triton/_C/libproton.so
triton/backends/__init__.py
triton/backends/compiler.py
triton/backends/driver.py
triton/backends/amd/__init__.py
triton/backends/amd/compiler.py
triton/backends/amd/driver.c
triton/backends/amd/driver.py
triton/backends/amd/include/hip/channel_descriptor.h
triton/backends/amd/include/hip/device_functions.h
triton/backends/amd/include/hip/driver_types.h
triton/backends/amd/include/hip/hip_bf16.h
triton/backends/amd/include/hip/hip_bfloat16.h
triton/backends/amd/include/hip/hip_common.h
triton/backends/amd/include/hip/hip_complex.h
triton/backends/amd/include/hip/hip_cooperative_groups.h
triton/backends/amd/include/hip/hip_deprecated.h
triton/backends/amd/include/hip/hip_ext.h
triton/backends/amd/include/hip/hip_fp16.h
triton/backends/amd/include/hip/hip_fp8.h
triton/backends/amd/include/hip/hip_gl_interop.h
triton/backends/amd/include/hip/hip_hcc.h
triton/backends/amd/include/hip/hip_math_constants.h
triton/backends/amd/include/hip/hip_profile.h
triton/backends/amd/include/hip/hip_runtime.h
triton/backends/amd/include/hip/hip_runtime_api.h
triton/backends/amd/include/hip/hip_texture_types.h
triton/backends/amd/include/hip/hip_vector_types.h
triton/backends/amd/include/hip/hip_version.h
triton/backends/amd/include/hip/hiprtc.h
triton/backends/amd/include/hip/library_types.h
triton/backends/amd/include/hip/math_functions.h
triton/backends/amd/include/hip/surface_types.h
triton/backends/amd/include/hip/texture_types.h
triton/backends/amd/include/hip/amd_detail/amd_channel_descriptor.h
triton/backends/amd/include/hip/amd_detail/amd_device_functions.h
triton/backends/amd/include/hip/amd_detail/amd_hip_atomic.h
triton/backends/amd/include/hip/amd_detail/amd_hip_bf16.h
triton/backends/amd/include/hip/amd_detail/amd_hip_bfloat16.h
dlcompiler-3.4.0.dist-info/LICENSE
dlcompiler-3.4.0.dist-info/METADATA
dlcompiler-3.4.0.dist-info/WHEEL
dlcompiler-3.4.0.dist-info/entry_points.txt
dlcompiler-3.4.0.dist-info/top_level.txt
dlcompiler-3.4.0.dist-info/RECORD
